{

"normalAttributeCap":50,
"maxAttributeCap":95,

"damagePenaltyValues":{
  "MELEE":7,
  "RANGED":10
},

"attributes":[
  {"name":"strength",
    "attack":{"MELEE_MODIFIER":{"x1":0,"y1":0.0,"x2":100,"y2":21}},
    "defend":{},
    "passive":{},
    "handling":{
      "STONE_AXE":{"x1":0,"y1":0.0,"x2":100,"y2":1.0},
      "IRON_AXE":{"x1":0,"y1":0.0,"x2":100,"y2":1.0},
      "DIAMOND_AXE":{"x1":0,"y1":0.0,"x2":100,"y2":1.0}
    },
    "description":"Melee damage, axe handling"
  },

  {"name":"precision",
    "attack":{
      "RANGED_MODIFIER":{"x1":0,"y1":0.0,"x2":100,"y2":30.0},
      "MELEE_ARMOUR_PENETRATION":{"x1":0,"y1":0.0,"x2":100,"y2":1.0},
      "RANGED_ARMOUR_PENETRATION":{"x1":0,"y1":0.0,"x2":100,"y2":1.0},
      "MAGIC_ARMOUR_PENETRATION":{"x1":0,"y1":0.0,"x2":100,"y2":1.0}
    },
    "defend":{},
    "passive":{},
    "handling":{
      "STONE_SPADE":{"x1":0,"y1":0.0,"x2":100,"y2":1.0},
      "IRON_SPADE":{"x1":0,"y1":0.0,"x2":100,"y2":1.0},
      "DIAMOND_SPADE":{"x1":0,"y1":0.0,"x2":100,"y2":1.0}
    },
    "description":"Ranged damage, armour pierce, shovel handling."
  },
  
  {"name":"willpower",
    "attack":{
      "MAGIC_MODIFIER":{"x1":0,"y1":0.0,"x2":100,"y2":18.0},
      "MELEE_ENCHANT_PENETRATION":{"x1":0,"y1":0.0,"x2":100,"y2":1.0},
      "RANGED_ENCHANT_PENETRATION":{"x1":0,"y1":0.0,"x2":100,"y2":1.0},
      "MAGIC_ENCHANT_PENETRATION":{"x1":0,"y1":0.0,"x2":100,"y2":1.0}
     },
    "defend":{},
    "passive":{},
    "handling":{
      "STONE_PICKAXE":{"x1":0,"y1":0.0,"x2":100,"y2":1.0},
      "IRON_PICKAXE":{"x1":0,"y1":0.0,"x2":100,"y2":1.0},
      "DIAMOND_PICKAXE":{"x1":0,"y1":0.0,"x2":100,"y2":1.0}
    },
    "description":"Magic damage, enchant pierce, pickaxe handling."
  },

  {"name":"toughness",
    "attack":{},
    "defend":{},
    "passive":{
    	"HEALTH_MODIFIER":{"x1":0,"y1":0.0,"x2":100,"y2":60.0}
    },
    "handling":{},
    "description":"Health bonus."
  },
  
  {"name":"luck",
    "attack":{},
    "defend":{},
    "passive":{
      "EXTRA_DROP_CHANCE_MODIFIER":{"x1":0,"y1":0,"x2":100,"y2":0.60}
    },
    "handling":{},
    "description":"Additional drops from blocks."
  }
]

}