{

"damageSkills":{
  "blade":{
    "name":"blade",
    "type":"OFFENSE",
    "attackerWeapons":["WOOD_SWORD","STONE_SWORD","IRON_SWORD","GOLD_SWORD","DIAMOND_SWORD"],
    "defenderWeapons":[],
    "attackerArmor":"ALL",
    "defenderArmor":"ALL",
    "attacker":"PLAYER",
    "defender":"ALL",
    "attack":"MELEE",
    "modifier":{"x1":0,"y1":0.0,"x2":50,"y2":30.0},
    "toolType":[],
    "toolDurability":{"x1":0,"y1":0.0,"x2":50,"y2":0.0}
  },

  "waraxe":{
    "name":"waraxe",
    "type":"OFFENSE",
    "attackerWeapons":["WOOD_AXE","STONE_AXE","IRON_AXE","GOLD_AXE","DIAMOND_AXE"],
    "defenderWeapons":[],
    "attackerArmor":"ALL",
    "defenderArmor":"ALL",
    "attacker":"PLAYER",
    "defender":"ALL",
    "attack":"MELEE",
    "modifier":{"x1":0,"y1":4.0,"x2":10,"y2":34.0},
    "toolType":[],
    "toolDurability":{"x1":0,"y1":0.0,"x2":50,"y2":0.0}
  },

  "archery":{
    "name":"archery",
    "type":"OFFENSE",
    "attackerWeapons":[],
    "defenderWeapons":[],
    "attackerArmor":"ALL",
    "defenderArmor":"ALL",
    "attacker":"PLAYER",
    "defender":"ALL",
    "attack":"RANGED",
    "modifier":{"x1":0,"y1":0.0,"x2":50,"y2":30.0},
    "toolType":[],
    "toolDurability":{"x1":0,"y1":0.0,"x2":50,"y2":0.0}
  },

  "magic":{
    "name":"magic",
    "type":"OFFENSE",
    "attackerWeapons":[],
    "defenderWeapons":[],
    "attackerArmor":"ALL",
    "defenderArmor":"ALL",
    "attacker":"PLAYER",
    "defender":"ALL",
    "attack":"MAGIC",
    "modifier":{"x1":0,"y1":0.0,"x2":50,"y2":40.0},
    "toolType":[],
    "toolDurability":{"x1":0,"y1":0.0,"x2":50,"y2":0.0}
  },

  "heavy armour":{
    "name":"heavy armour",
    "type":"DEFENSE",
    "attackerWeapons":[],
    "defenderWeapons":[],
    "attackerArmor":"ALL",
    "defenderArmor":"HEAVY",
    "attacker":"ALL",
    "defender":"ALL",
    "attack":"PHYSICAL",
    "modifier":{"x1":0,"y1":0.0,"x2":50,"y2":-30.0},
    "toolType":[],
    "toolDurability":{"x1":0,"y1":0.0,"x2":50,"y2":0.0}
  },

  "light armour":{
    "name":"light armour",
    "type":"DEFENSE",
    "attackerWeapons":[],
    "defenderWeapons":[],
    "attackerArmor":"ALL",
    "defenderArmor":"LIGHT",
    "attacker":"ALL",
    "defender":"ALL",
    "attack":"PHYSICAL",
    "modifier":{"x1":0,"y1":0.0,"x2":50,"y2":-30.0},
    "toolType":[],
    "toolDurability":{"x1":0,"y1":0.0,"x2":50,"y2":0.0}
  },

  "unarmoured":{
    "name":"unarmoured",
    "type":"DEFENSE",
    "attackerWeapons":[],
    "defenderWeapons":[],
    "attackerArmor":"ALL",
    "defenderArmor":"UNARMOURED",
    "attacker":"ALL",
    "defender":"ALL",
    "attack":"PHYSICAL",
    "modifier":{"x1":0,"y1":0.0,"x2":50,"y2":-30.0},
    "toolType":[],
    "toolDurability":{"x1":0,"y1":0.0,"x2":50,"y2":0.0}
  },

  "magic warding":{
    "name":"magic warding",
    "type":"DEFENSE",
    "attackerWeapons":[],
    "defenderWeapons":[],
    "attackerArmor":"ALL",
    "defenderArmor":"ALL",
    "attacker":"ALL",
    "defender":"ALL",
    "attack":"MAGIC",
    "modifier":{"x1":0,"y1":0.0,"x2":50,"y2":-40.0},
    "toolType":[],
    "toolDurability":{"x1":0,"y1":0.0,"x2":50,"y2":0.0}
  },

  "woodcutting":{
    "name":"woodcutting",
    "type":"BLOCK",
    "attackerWeapons":[],
    "defenderWeapons":[],
    "attackerArmor":"ALL",
    "defenderArmor":"ALL",
    "attacker":"ALL",
    "defender":"ALL",
    "attack":"NONE",
    "modifier":{"x1":0,"y1":0.0,"x2":50,"y2":0.0},
    "toolType":["WOOD_AXE","STONE_AXE","IRON_AXE","GOLD_AXE","DIAMOND_AXE"],
    "toolDurability":{"x1":0,"y1":0.0,"x2":50,"y2":0.8}
  },

  "mining":{
    "name":"mining",
    "type":"BLOCK",
    "attackerWeapons":[],
    "defenderWeapons":[],
    "attackerArmor":"ALL",
    "defenderArmor":"ALL",
    "attacker":"ALL",
    "defender":"ALL",
    "attack":"NONE",
    "modifier":{"x1":0,"y1":0.0,"x2":50,"y2":0.0},
    "toolType":[
      "WOOD_PICKAXE","STONE_PICKAXE","IRON_PICKAXE","GOLD_PICKAXE","DIAMOND_PICKAXE",
      "WOOD_SPADE","STONE_SPADE","IRON_SPADE","GOLD_SPADE","DIAMOND_SPADE"
    ],
    "toolDurability":{"x1":0,"y1":0.0,"x2":50,"y2":0.6}
  },

  "farming":{
    "name":"farming",
    "type":"BLOCK",
    "attackerWeapons":[],
    "defenderWeapons":[],
    "attackerArmor":"ALL",
    "defenderArmor":"ALL",
    "attacker":"ALL",
    "defender":"ALL",
    "attack":"NONE",
    "modifier":{"x1":0,"y1":0.0,"x2":50,"y2":0.0},
    "toolType":["WOOD_HOE","STONE_HOE","IRON_HOE","GOLD_HOE","DIAMOND_HOE"],
    "toolDurability":{"x1":0,"y1":0.0,"x2":50,"y2":0.0}
  },

  "smithing":{
    "name":"smithing",
    "type":"BLOCK",
    "attackerWeapons":[],
    "defenderWeapons":[],
    "attackerArmor":"ALL",
    "defenderArmor":"ALL",
    "attacker":"ALL",
    "defender":"ALL",
    "attack":"NONE",
    "modifier":{"x1":0,"y1":0.0,"x2":50,"y2":0.0},
    "toolType":[
      "IRON_PICKAXE","IRON_SPADE","IRON_AXE",
      "DIAMOND_PICKAXE","DIAMOND_SPADE","DIAMOND_AXE"
    ],
    "toolDurability":{"x1":0,"y1":0.0,"x2":50,"y2":0.4}
  }

}

}